pycapo/__init__.py
pycapo/_constants.py
pycapo/_version.py
pycapo/commands.py
pycapo/models.py
tests/__init__.py
tests/test_path.py
tests/test_profile.py
tests/test_properties.py
tests/test_pycapo.py
tests/test_data/__init__.py
pycapo-0.3.1.dist-info/LICENSE.txt
pycapo-0.3.1.dist-info/METADATA
pycapo-0.3.1.dist-info/WHEEL
pycapo-0.3.1.dist-info/entry_points.txt
pycapo-0.3.1.dist-info/top_level.txt
pycapo-0.3.1.dist-info/RECORD
