Metadata-Version: 2.1
Name: pycapo
Version: 0.3.1
Summary: CAPO (CASA, Archive, and Pipeline Options) for Python
Home-page: https://open-bitbucket.nrao.edu/projects/SSA/repos/pycapo
Author: Stephan Witz
Author-email: switz@nrao.edu
Maintainer: Janet L. Goldstein
Maintainer-email: jgoldste@nrao.edu
License: GPL
Platform: UNKNOWN
Classifier: Development Status :: 4 - Beta
Classifier: Intended Audience :: Developers
Classifier: Topic :: Software Development :: Build Tools
Classifier: License :: OSI Approved :: GNU General Public License v2 (GPLv2)
Classifier: Programming Language :: Python :: 2
Classifier: Programming Language :: Python :: 2.7
Classifier: Programming Language :: Python :: 3
Classifier: Programming Language :: Python :: 3.4
Classifier: Programming Language :: Python :: 3.5
Classifier: Programming Language :: Python :: 3.6
Classifier: Programming Language :: Python :: 3.7
Classifier: Programming Language :: Python :: 3.8
